snooper/__init__.py
snooper/snooper.py
snooper-0.3.0.dist-info/DESCRIPTION.rst
snooper-0.3.0.dist-info/METADATA
snooper-0.3.0.dist-info/RECORD
snooper-0.3.0.dist-info/WHEEL
snooper-0.3.0.dist-info/entry_points.txt
snooper-0.3.0.dist-info/metadata.json
snooper-0.3.0.dist-info/top_level.txt
