Metadata-Version: 2.0
Name: snooper
Version: 0.3.0
Summary: Snooper provides a simple way for finding AWS resources.
Home-page: https://github.com/kintoandar/snooper
Author: Joel Bastos
Author-email: kintoandar@gmail.com
License: MIT license
Keywords: snooper
Platform: UNKNOWN
Classifier: Development Status :: 2 - Pre-Alpha
Classifier: Intended Audience :: Developers
Classifier: License :: OSI Approved :: MIT License
Classifier: Natural Language :: English
Classifier: Programming Language :: Python :: 2
Classifier: Programming Language :: Python :: 2.6
Classifier: Programming Language :: Python :: 2.7
Classifier: Programming Language :: Python :: 3
Classifier: Programming Language :: Python :: 3.3
Classifier: Programming Language :: Python :: 3.4
Classifier: Programming Language :: Python :: 3.5
Requires-Dist: Click (>=6.0)
Requires-Dist: boto3 (>=1.4.4)
